{
  "_id": "603MCbBWbeCYGK3p",
  "name": "Magical Secrets",
  "type": "feat",
  "system": {
    "description": {
      "value": "<div class=\"rd__b  rd__b--3\"><p>By 10th level, you have plundered magical knowledge from a wide spectrum of disciplines. Choose two spells from any classes, including this one. A spell you choose must be of a level you can cast, as shown on the Bard table, or a cantrip.</p><p>The chosen spells count as bard spells for you and are included in the number in the Spells Known column of the Bard table.</p><p>You learn two additional spells from any classes at 14th level and again at 18th level.</p></div>",
      "chat": ""
    },
    "source": {
      "custom": "",
      "book": "PHB'14",
      "page": "51",
      "license": "",
      "rules": "2014",
      "revision": 1
    },
    "uses": {
      "max": "",
      "spent": 0,
      "recovery": []
    },
    "type": {
      "value": "class",
      "subtype": ""
    },
    "requirements": "Bard 10",
    "properties": [],
    "activities": {},
    "enchant": {},
    "prerequisites": {
      "level": null,
      "repeatable": false
    },
    "identifier": "magical-secrets",
    "advancement": [],
    "cover": null,
    "crewed": false
  },
  "ownership": {
    "default": 0,
    "ox2bho65epIfC0E1": 3
  },
  "effects": [],
  "flags": {},
  "img": "icons/sundries/documents/document-torn-diagram-tan.webp",
  "folder": "uU9E1kOnadd1jQvu",
  "_stats": {
    "compendiumSource": null,
    "duplicateSource": null,
    "coreVersion": "12.331",
    "systemId": "dnd5e",
    "systemVersion": "4.3.5",
    "createdTime": 1741926055715,
    "modifiedTime": 1741926055715,
    "lastModifiedBy": "ox2bho65epIfC0E1"
  },
  "sort": 0,
  "_key": "!items!603MCbBWbeCYGK3p"
}
